[
	{"id":"1", "num":7, "name":"C-Ronaldo", "position":"FW", "team":"葡萄牙", "thumb":"C-Ronaldo.png", "votes":4},
	{"id":"2", "num":22, "name":"Dzyuba", "position":"FW", "team":"俄罗斯", "thumb":"Dzyuba.png", "votes":3},
	{"id":"3", "num":9, "name":"Kane", "position":"FW", "team":"英格兰", "thumb":"Kane.png", "votes":5},
	{"id":"4", "num":3, "name":"Cheryshev", "position":"CMF", "team":"俄罗斯", "thumb":"Cheryshev.png", "votes":3},
	{"id":"5", "num":21, "name":"Cavani", "position":"FW", "team":"乌拉圭", "thumb":"Cavani.png", "votes":3},
	{"id":"6", "num":9, "name":"Lukaku", "position":"FW", "team":"比利时", "thumb":"Lukaku.png", "votes":4},
	{"id":"7", "num":10, "name":"Khazri", "position":"FW", "team":"突尼斯", "thumb":"Khazri.png", "votes":2},
	{"id":"8", "num":10, "name":"Mbappe", "position":"FW", "team":"法国", "thumb":"Mbappe.png", "votes":3},
	{"id":"9", "num":19, "name":"Costa", "position":"FW", "team":"西班牙", "thumb":"Costa.png", "votes":3},
	{"id":"10", "num":10, "name":"Hazard", "position":"FW", "team":"比利时", "thumb":"Hazard.png", "votes":2}
]